django_bootmin/__init__.py
django_bootmin/apps.py
django_bootmin/base.py
django_bootmin/filters.py
django_bootmin/mixins.py
django_bootmin/settings.py
django_bootmin/sites.py
django_bootmin/version.py
django_bootmin/templates/admin/base.html
django_bootmin/templates/admin/confirmation.html
django_bootmin/templates/admin/form_view.html
django_bootmin/templates/admin/inspect.html
django_bootmin/templates/admin/inspect_object_tools.html
django_bootmin/templates/admin/object_buttons.html
django_bootmin/templates/admin/print.html
django_bootmin/templates/admin/print_cover.html
django_bootmin/templates/admin/print_footer.html
django_bootmin/templates/admin/print_header.html
django_bootmin-0.1.3.dist-info/METADATA
django_bootmin-0.1.3.dist-info/WHEEL
django_bootmin-0.1.3.dist-info/top_level.txt
django_bootmin-0.1.3.dist-info/RECORD
